[
  {
    "template_name": "AXUV016_4513_锯齿测试",
    "raw_query_pattern": [
      {
        "x": 32,
        "y": 84,
        "handleIn": {
          "x": 0,
          "y": 0
        },
        "handleOut": {
          "x": 0,
          "y": -2.467593598503214
        }
      },
      {
        "x": 40,
        "y": 95,
        "handleIn": {
          "x": -0.5589561180917855,
          "y": -1.117912236183571
        },
        "handleOut": {
          "x": 3.569994195242458,
          "y": 7.139988390484916
        }
      },
      {
        "x": 52,
        "y": 116,
        "handleIn": {
          "x": -3.829294462333152,
          "y": -7.020373180944119
        },
        "handleOut": {
          "x": 10.229201300162941,
          "y": 18.753535716965402
        }
      },
      {
        "x": 96,
        "y": 180,
        "handleIn": {
          "x": -14.083458271152608,
          "y": -14.083458271152608
        },
        "handleOut": {
          "x": 1.1583023806100812,
          "y": 1.1583023806100812
        }
      },
      {
        "x": 100,
        "y": 160,
        "handleIn": {
          "x": -0.41898249750842353,
          "y": 2.094912487542146
        },
        "handleOut": {
          "x": 2.6751456147901678,
          "y": -13.375728073950839
        }
      },
      {
        "x": 109,
        "y": 120,
        "handleIn": {
          "x": -2.711802494660759,
          "y": 13.559012473303767
        },
        "handleOut": {
          "x": 0.472690096930819,
          "y": -2.3634504846541233
        }
      },
      {
        "x": 115,
        "y": 98,
        "handleIn": {
          "x": -1.8488356754772326,
          "y": -1.8488356754772326
        },
        "handleOut": {
          "x": 14.709806461492832,
          "y": 14.709806461492832
        }
      },
      {
        "x": 147,
        "y": 167,
        "handleIn": {
          "x": -4.863504836137395,
          "y": -4.863504836137409
        },
        "handleOut": {
          "x": 3.947519429448164,
          "y": 3.9475194294481497
        }
      },
      {
        "x": 158,
        "y": 182,
        "handleIn": {
          "x": -2.7651948724939928,
          "y": -5.530389744988014
        },
        "handleOut": {
          "x": 1.4063348739819332,
          "y": 2.8126697479638665
        }
      },
      {
        "x": 163,
        "y": 190,
        "handleIn": {
          "x": -2.8126697479638665,
          "y": 1.4063348739819332
        },
        "handleOut": {
          "x": 1.725430305688235,
          "y": -0.8627151528441175
        }
      },
      {
        "x": 164,
        "y": 183,
        "handleIn": {
          "x": 0,
          "y": 1.2282880235686804
        },
        "handleOut": {
          "x": 0,
          "y": -23.149101801177792
        }
      },
      {
        "x": 178,
        "y": 115,
        "handleIn": {
          "x": 0,
          "y": 23.216237514371656
        },
        "handleOut": {
          "x": 0,
          "y": -0.9090483880720512
        }
      },
      {
        "x": 180,
        "y": 106,
        "handleIn": {
          "x": 0,
          "y": 0
        },
        "handleOut": {
          "x": 0,
          "y": 0
        }
      },
      {
        "x": 185,
        "y": 132,
        "handleIn": {
          "x": -0.28806623147238497,
          "y": -1.1522649258895825
        },
        "handleOut": {
          "x": 2.525153449746284,
          "y": 10.100613798985151
        }
      },
      {
        "x": 216,
        "y": 222,
        "handleIn": {
          "x": -5.866283097168832,
          "y": -5.866283097168846
        },
        "handleOut": {
          "x": 1.4291921025132694,
          "y": 1.4291921025132837
        }
      },
      {
        "x": 217,
        "y": 218,
        "handleIn": {
          "x": -0.12332948358357498,
          "y": 0.3699884507507427
        },
        "handleOut": {
          "x": 2.359948699003354,
          "y": -7.079846097010041
        }
      },
      {
        "x": 221,
        "y": 197,
        "handleIn": {
          "x": -1.050993131680002,
          "y": 7.356951921759915
        },
        "handleOut": {
          "x": 3.028002385816052,
          "y": -21.19601670071232
        }
      },
      {
        "x": 237,
        "y": 130,
        "handleIn": {
          "x": 0,
          "y": 21.427251812246666
        },
        "handleOut": {
          "x": 0,
          "y": -0.5542929029128061
        }
      },
      {
        "x": 239,
        "y": 121,
        "handleIn": {
          "x": 0,
          "y": 0
        },
        "handleOut": {
          "x": 0,
          "y": 0
        }
      },
      {
        "x": 239,
        "y": 124,
        "handleIn": {
          "x": 0,
          "y": -1
        },
        "handleOut": {
          "x": 0,
          "y": 7.31252146298975
        }
      },
      {
        "x": 247,
        "y": 144,
        "handleIn": {
          "x": -4.005360621229329,
          "y": -6.008040931843993
        },
        "handleOut": {
          "x": 7.0256576326452205,
          "y": 10.53848644896783
        }
      },
      {
        "x": 281,
        "y": 200,
        "handleIn": {
          "x": -2.1336549884574083,
          "y": -8.534619953829704
        },
        "handleOut": {
          "x": 1.1649545966172923,
          "y": 4.659818386469112
        }
      },
      {
        "x": 286,
        "y": 220,
        "handleIn": {
          "x": -4.041590772433494,
          "y": -2.02079538621674
        },
        "handleOut": {
          "x": 0.5251838916705083,
          "y": 0.26259194583526124
        }
      },
      {
        "x": 289,
        "y": 193,
        "handleIn": {
          "x": -0.27801287456776436,
          "y": 2.502115871109744
        },
        "handleOut": {
          "x": 1.7706677850410983,
          "y": -15.936010065370127
        }
      },
      {
        "x": 300,
        "y": 139,
        "handleIn": {
          "x": -7.185621908233372,
          "y": 14.371243816466787
        },
        "handleOut": {
          "x": 2.83597480839353,
          "y": -5.671949616787018
        }
      },
      {
        "x": 306,
        "y": 114,
        "handleIn": {
          "x": 0,
          "y": 4.238940371478833
        },
        "handleOut": {
          "x": 0,
          "y": -0.3333333333333428
        }
      },
      {
        "x": 306,
        "y": 113,
        "handleIn": {
          "x": 0,
          "y": -0.3333333333333428
        },
        "handleOut": {
          "x": 0,
          "y": 21.12121690275424
        }
      },
      {
        "x": 338,
        "y": 179,
        "handleIn": {
          "x": -9.336847217774505,
          "y": -18.67369443554901
        },
        "handleOut": {
          "x": 3.9179208008839623,
          "y": 7.835841601767974
        }
      },
      {
        "x": 347,
        "y": 204,
        "handleIn": {
          "x": -1.741959150434866,
          "y": -8.709795752174244
        },
        "handleOut": {
          "x": 0.6825041873951818,
          "y": 3.4125209369759375
        }
      },
      {
        "x": 350,
        "y": 214,
        "handleIn": {
          "x": -2.4608038433722186,
          "y": 2.460803843372233
        },
        "handleOut": {
          "x": 5.240039532503658,
          "y": -5.240039532503658
        }
      },
      {
        "x": 356,
        "y": 182,
        "handleIn": {
          "x": -2.81254306704119,
          "y": 7.500114845443186
        },
        "handleOut": {
          "x": 0.8956124924931146,
          "y": -2.3882999799816105
        }
      },
      {
        "x": 381,
        "y": 90,
        "handleIn": {
          "x": 0,
          "y": 2.5406772325852103
        },
        "handleOut": {
          "x": 0,
          "y": 0
        }
      }
    ],
    "parameters": {
      "lowpassAmplitude": 0.004,
      "xFilterRange": [
        null,
        null
      ],
      "yFilterRange": [
        null,
        null
      ],
      "patternRepeatCount": 0,
      "maxMatchPerChannel": 10,
      "amplitudeLimit": null,
      "timeSpanLimit": null
    },
    "description": "小测试~",
    "created_time": "2025-06-09T23:04:50.133760+00:00",
    "last_modified": "2025-06-09T23:04:50.133800+00:00"
  },
  {
    "template_name": "test",
    "raw_query_pattern": [
      {
        "x": 119,
        "y": 68,
        "handleIn": {
          "x": 0,
          "y": 0
        },
        "handleOut": {
          "x": 13.666666666666657,
          "y": 23.333333333333343
        }
      },
      {
        "x": 160,
        "y": 138,
        "handleIn": {
          "x": -13.959168764567977,
          "y": -23.159529995760522
        },
        "handleOut": {
          "x": 8.109327399648805,
          "y": 13.454111367599168
        }
      },
      {
        "x": 199,
        "y": 169,
        "handleIn": {
          "x": -13.138008497482474,
          "y": -7.507433427132838
        },
        "handleOut": {
          "x": 2.909614165851849,
          "y": 1.6626366662010525
        }
      },
      {
        "x": 220,
        "y": 181,
        "handleIn": {
          "x": -3.7545933255841533,
          "y": 2.5030622170561045
        },
        "handleOut": {
          "x": 13.323977358375714,
          "y": -8.88265157225048
        }
      },
      {
        "x": 291,
        "y": 66,
        "handleIn": {
          "x": -4.697696873095936,
          "y": 9.395393746191843
        },
        "handleOut": {
          "x": 0,
          "y": 0
        }
      }
    ],
    "parameters": {
      "lowpassAmplitude": 0.004,
      "xFilterRange": [
        null,
        null
      ],
      "yFilterRange": [
        null,
        null
      ],
      "patternRepeatCount": 0,
      "maxMatchPerChannel": 10,
      "amplitudeLimit": null,
      "timeSpanLimit": null
    },
    "description": "1-100test",
    "created_time": "2025-06-16T12:53:00.732782+00:00",
    "last_modified": "2025-06-16T12:53:00.732820+00:00"
  }
]